dataqualityx/AlterUtil.py
dataqualityx/DateUtil.py
dataqualityx/DbUtil.py
dataqualityx/__init__.py
dataqualityx/app.py
dataqualityx-0.1.2.dist-info/LICENSE
dataqualityx-0.1.2.dist-info/METADATA
dataqualityx-0.1.2.dist-info/WHEEL
dataqualityx-0.1.2.dist-info/entry_points.txt
dataqualityx-0.1.2.dist-info/top_level.txt
dataqualityx-0.1.2.dist-info/RECORD
