Metadata-Version: 2.1
Name: dataqualityx
Version: 0.1.2
Summary: data quality
Home-page: https://github.com/zzzzzzzs/dataqualityx
Author: zzzzzzzs
Author-email: 1443539042@qq.com
License-File: LICENSE
